Metadata-Version: 1.1
Name: aks-calc
Version: 1.1.1
Summary: A very basic calculator
Home-page: UNKNOWN
Author: Akshay Kumar
Author-email: akshaykrsingh490@gmail.com
License: MIT
Keywords: calculator
Platform: UNKNOWN
Classifier: Development Status :: 5 - Production/Stable
Classifier: Intended Audience :: Education
Classifier: License :: OSI Approved :: MIT License
Classifier: Programming Language :: Python :: 3
Classifier: Programming Language :: Python :: 3.4
Classifier: Programming Language :: Python :: 3.5
Classifier: Programming Language :: Python :: 3.8
Classifier: Programming Language :: Python :: 3.9
